{
  "batchId": "batch_1759401182431",
  "buildingId": "Altitude Columbus",
  "coordRef": "test_local_map",
  "count": 50,
  "deviceId": "OnePlusThreePJE110-15",
  "endTimeMs": 0,
  "floorId": "3rd floor",
  "mapId": "Room 2320",
  "points": [
    {
      "accepted": true,
      "anchorsUsed": 6,
      "dt": 0.096,
      "rms": 2.9872965069020987,
      "time": 1759401179040,
      "velocity": 0.05671274367197952,
      "x": -0.9892884854830638,
      "y": 3.675190176148668
    },
    {
      "accepted": true,
      "anchorsUsed": 6,
      "dt": 0.047,
      "rms": 2.9872965069020987,
      "time": 1759401179087,
      "velocity": 0.059045618421718495,
      "x": -0.9892884854830638,
      "y": 3.675190176148668
    },
    {
      "accepted": true,
      "anchorsUsed": 6,
      "dt": 0.043,
      "rms": 2.9872965069020987,
      "time": 1759401179130,
      "velocity": 0.061651327255289524,
      "x": -0.9892884854830638,
      "y": 3.675190176148668
    },
    {
      "accepted": true,
      "anchorsUsed": 6,
      "dt": 0.048,
      "rms": 2.9872965069020987,
      "time": 1759401179178,
      "velocity": 0.06440920154501087,
      "x": -0.9892884854830638,
      "y": 3.675190176148668
    },
    {
      "accepted": true,
      "anchorsUsed": 6,
      "dt": 0.045,
      "rms": 2.9872965069020987,
      "time": 1759401179223,
      "velocity": 0.06722302935111472,
      "x": -0.9892884854830638,
      "y": 3.675190176148668
    },
    {
      "accepted": true,
      "anchorsUsed": 6,
      "dt": 0.046,
      "rms": 2.9872965069020987,
      "time": 1759401179269,
      "velocity": 0.07002492793087757,
      "x": -0.9892884854830638,
      "y": 3.675190176148668
    },
    {
      "accepted": true,
      "anchorsUsed": 6,
      "dt": 0.046,
      "rms": 2.9872965069020987,
      "time": 1759401179315,
      "velocity": 0.07276545178536946,
      "x": -0.9892884854830638,
      "y": 3.675190176148668
    },
    {
      "accepted": true,
      "anchorsUsed": 6,
      "dt": 0.048,
      "rms": 3.0725602815849764,
      "time": 1759401179363,
      "velocity": 0.0699288313207467,
      "x": -1.148855635520756,
      "y": 3.4860874622850373
    },
    {
      "accepted": true,
      "anchorsUsed": 6,
      "dt": 0.047,
      "rms": 3.0725602815849764,
      "time": 1759401179410,
      "velocity": 0.06717336952445177,
      "x": -1.148855635520756,
      "y": 3.4860874622850373
    },
    {
      "accepted": true,
      "anchorsUsed": 6,
      "dt": 0.047,
      "rms": 3.0725602815849764,
      "time": 1759401179457,
      "velocity": 0.06449777938171658,
      "x": -1.148855635520756,
      "y": 3.4860874622850373
    },
    {
      "accepted": true,
      "anchorsUsed": 6,
      "dt": 0.05,
      "rms": 3.0725602815849764,
      "time": 1759401179507,
      "velocity": 0.061889478507191065,
      "x": -1.148855635520756,
      "y": 3.4860874622850373
    },
    {
      "accepted": true,
      "anchorsUsed": 6,
      "dt": 0.048,
      "rms": 3.0725602815849764,
      "time": 1759401179555,
      "velocity": 0.0593559073532546,
      "x": -1.148855635520756,
      "y": 3.4860874622850373
    },
    {
      "accepted": true,
      "anchorsUsed": 6,
      "dt": 0.048,
      "rms": 3.0725602815849764,
      "time": 1759401179603,
      "velocity": 0.05689609147058483,
      "x": -1.148855635520756,
      "y": 3.4860874622850373
    },
    {
      "accepted": true,
      "anchorsUsed": 6,
      "dt": 0.049,
      "rms": 3.0725602815849764,
      "time": 1759401179652,
      "velocity": 0.05450563480486171,
      "x": -1.148855635520756,
      "y": 3.4860874622850373
    },
    {
      "accepted": true,
      "anchorsUsed": 6,
      "dt": 0.048,
      "rms": 3.0725602815849764,
      "time": 1759401179700,
      "velocity": 0.052187177437807944,
      "x": -1.148855635520756,
      "y": 3.4860874622850373
    },
    {
      "accepted": true,
      "anchorsUsed": 6,
      "dt": 0.049,
      "rms": 3.0725602815849764,
      "time": 1759401179749,
      "velocity": 0.04993645707627337,
      "x": -1.148855635520756,
      "y": 3.4860874622850373
    },
    {
      "accepted": true,
      "anchorsUsed": 6,
      "dt": 0.05,
      "rms": 3.0725602815849764,
      "time": 1759401179799,
      "velocity": 0.047749741044656,
      "x": -1.148855635520756,
      "y": 3.4860874622850373
    },
    {
      "accepted": true,
      "anchorsUsed": 6,
      "dt": 0.053,
      "rms": 3.0725602815849764,
      "time": 1759401179852,
      "velocity": 0.045617938309909616,
      "x": -1.148855635520756,
      "y": 3.4860874622850373
    },
    {
      "accepted": true,
      "anchorsUsed": 6,
      "dt": 0.049,
      "rms": 3.0725602815849764,
      "time": 1759401179901,
      "velocity": 0.04355307324738022,
      "x": -1.148855635520756,
      "y": 3.4860874622850373
    },
    {
      "accepted": true,
      "anchorsUsed": 6,
      "dt": 0.051,
      "rms": 3.0725602815849764,
      "time": 1759401179952,
      "velocity": 0.041548781401502435,
      "x": -1.148855635520756,
      "y": 3.4860874622850373
    },
    {
      "accepted": true,
      "anchorsUsed": 6,
      "dt": 0.051,
      "rms": 3.0725602815849764,
      "time": 1759401180003,
      "velocity": 0.03960486545916583,
      "x": -1.148855635520756,
      "y": 3.4860874622850373
    },
    {
      "accepted": true,
      "anchorsUsed": 6,
      "dt": 0.052,
      "rms": 3.0725602815849764,
      "time": 1759401180055,
      "velocity": 0.03771854916892199,
      "x": -1.148855635520756,
      "y": 3.4860874622850373
    },
    {
      "accepted": true,
      "anchorsUsed": 6,
      "dt": 0.051,
      "rms": 3.0725602815849764,
      "time": 1759401180106,
      "velocity": 0.03589229153748673,
      "x": -1.148855635520756,
      "y": 3.4860874622850373
    },
    {
      "accepted": true,
      "anchorsUsed": 6,
      "dt": 0.055,
      "rms": 3.0725602815849764,
      "time": 1759401180161,
      "velocity": 0.03411639590576947,
      "x": -1.148855635520756,
      "y": 3.4860874622850373
    },
    {
      "accepted": true,
      "anchorsUsed": 6,
      "dt": 0.051,
      "rms": 3.0725602815849764,
      "time": 1759401180212,
      "velocity": 0.032400777842239104,
      "x": -1.148855635520756,
      "y": 3.4860874622850373
    },
    {
      "accepted": true,
      "anchorsUsed": 6,
      "dt": 0.05,
      "rms": 3.0725602815849764,
      "time": 1759401180262,
      "velocity": 0.03074709854962257,
      "x": -1.148855635520756,
      "y": 3.4860874622850373
    },
    {
      "accepted": true,
      "anchorsUsed": 6,
      "dt": 0.053,
      "rms": 3.0725602815849764,
      "time": 1759401180315,
      "velocity": 0.029148366486784913,
      "x": -1.148855635520756,
      "y": 3.4860874622850373
    },
    {
      "accepted": true,
      "anchorsUsed": 6,
      "dt": 0.053,
      "rms": 3.0725602815849764,
      "time": 1759401180368,
      "velocity": 0.027604759834316046,
      "x": -1.148855635520756,
      "y": 3.4860874622850373
    },
    {
      "accepted": true,
      "anchorsUsed": 6,
      "dt": 0.053,
      "rms": 3.0725602815849764,
      "time": 1759401180421,
      "velocity": 0.02611643846984288,
      "x": -1.148855635520756,
      "y": 3.4860874622850373
    },
    {
      "accepted": true,
      "anchorsUsed": 6,
      "dt": 0.057,
      "rms": 3.0725602815849764,
      "time": 1759401180478,
      "velocity": 0.024676269015685447,
      "x": -1.148855635520756,
      "y": 3.4860874622850373
    },
    {
      "accepted": true,
      "anchorsUsed": 6,
      "dt": 0.054,
      "rms": 3.0725602815849764,
      "time": 1759401180532,
      "velocity": 0.023290807238545225,
      "x": -1.148855635520756,
      "y": 3.4860874622850373
    },
    {
      "accepted": true,
      "anchorsUsed": 6,
      "dt": 0.055,
      "rms": 2.1812034768678417,
      "time": 1759401180587,
      "velocity": 0.0315665593018164,
      "x": -2.4756290830870764,
      "y": 3.4606348681991665
    },
    {
      "accepted": true,
      "anchorsUsed": 6,
      "dt": 0.054,
      "rms": 2.1812034768678417,
      "time": 1759401180641,
      "velocity": 0.06672897990857433,
      "x": -2.4756290830870764,
      "y": 3.4606348681991665
    },
    {
      "accepted": true,
      "anchorsUsed": 6,
      "dt": 0.056,
      "rms": 2.1812034768678417,
      "time": 1759401180697,
      "velocity": 0.10094778577781187,
      "x": -2.4756290830870764,
      "y": 3.4606348681991665
    },
    {
      "accepted": true,
      "anchorsUsed": 6,
      "dt": 0.055,
      "rms": 2.1812034768678417,
      "time": 1759401180752,
      "velocity": 0.1327423290454741,
      "x": -2.4756290830870764,
      "y": 3.4606348681991665
    },
    {
      "accepted": true,
      "anchorsUsed": 6,
      "dt": 0.063,
      "rms": 2.171610106456242,
      "time": 1759401180815,
      "velocity": 0.16267249462638586,
      "x": -2.475483938679938,
      "y": 3.6431488121819444
    },
    {
      "accepted": true,
      "anchorsUsed": 6,
      "dt": 0.056,
      "rms": 2.171610106456242,
      "time": 1759401180871,
      "velocity": 0.19014649359986494,
      "x": -2.475483938679938,
      "y": 3.6431488121819444
    },
    {
      "accepted": true,
      "anchorsUsed": 6,
      "dt": 0.057,
      "rms": 2.171610106456242,
      "time": 1759401180928,
      "velocity": 0.2153675107155207,
      "x": -2.475483938679938,
      "y": 3.6431488121819444
    },
    {
      "accepted": true,
      "anchorsUsed": 6,
      "dt": 0.056,
      "rms": 2.171610106456242,
      "time": 1759401180984,
      "velocity": 0.23848029663120704,
      "x": -2.475483938679938,
      "y": 3.6431488121819444
    },
    {
      "accepted": true,
      "anchorsUsed": 6,
      "dt": 0.057,
      "rms": 2.171610106456242,
      "time": 1759401181041,
      "velocity": 0.25964676368164674,
      "x": -2.475483938679938,
      "y": 3.6431488121819444
    },
    {
      "accepted": true,
      "anchorsUsed": 6,
      "dt": 0.058,
      "rms": 2.171610106456242,
      "time": 1759401181099,
      "velocity": 0.2790056270536838,
      "x": -2.475483938679938,
      "y": 3.6431488121819444
    },
    {
      "accepted": true,
      "anchorsUsed": 6,
      "dt": 0.06,
      "rms": 2.171610106456242,
      "time": 1759401181159,
      "velocity": 0.2966846366683806,
      "x": -2.475483938679938,
      "y": 3.6431488121819444
    },
    {
      "accepted": true,
      "anchorsUsed": 6,
      "dt": 0.059,
      "rms": 2.171610106456242,
      "time": 1759401181218,
      "velocity": 0.3127680881888089,
      "x": -2.475483938679938,
      "y": 3.6431488121819444
    },
    {
      "accepted": true,
      "anchorsUsed": 6,
      "dt": 0.058,
      "rms": 2.171610106456242,
      "time": 1759401181276,
      "velocity": 0.327339038226799,
      "x": -2.475483938679938,
      "y": 3.6431488121819444
    },
    {
      "accepted": true,
      "anchorsUsed": 6,
      "dt": 0.059,
      "rms": 2.171610106456242,
      "time": 1759401181335,
      "velocity": 0.3404856759894323,
      "x": -2.475483938679938,
      "y": 3.6431488121819444
    },
    {
      "accepted": true,
      "anchorsUsed": 6,
      "dt": 0.059,
      "rms": 2.171610106456242,
      "time": 1759401181394,
      "velocity": 0.3522824239619891,
      "x": -2.475483938679938,
      "y": 3.6431488121819444
    },
    {
      "accepted": true,
      "anchorsUsed": 6,
      "dt": 0.064,
      "rms": 2.171610106456242,
      "time": 1759401181458,
      "velocity": 0.36279927420744706,
      "x": -2.475483938679938,
      "y": 3.6431488121819444
    },
    {
      "accepted": true,
      "anchorsUsed": 6,
      "dt": 0.056,
      "rms": 2.171610106456242,
      "time": 1759401181514,
      "velocity": 0.3720956656796672,
      "x": -2.475483938679938,
      "y": 3.6431488121819444
    },
    {
      "accepted": true,
      "anchorsUsed": 6,
      "dt": 0.055,
      "rms": 2.171610106456242,
      "time": 1759401181569,
      "velocity": 0.3802442434233797,
      "x": -2.475483938679938,
      "y": 3.6431488121819444
    },
    {
      "accepted": true,
      "anchorsUsed": 6,
      "dt": 0.06,
      "rms": 2.171610106456242,
      "time": 1759401181629,
      "velocity": 0.3872930628505532,
      "x": -2.475483938679938,
      "y": 3.6431488121819444
    },
    {
      "accepted": true,
      "anchorsUsed": 6,
      "dt": 0.06,
      "rms": 2.171610106456242,
      "time": 1759401181689,
      "velocity": 0.3932929649225061,
      "x": -2.475483938679938,
      "y": 3.6431488121819444
    },
    {
      "accepted": true,
      "anchorsUsed": 6,
      "dt": 0.062,
      "rms": 2.171610106456242,
      "time": 1759401181751,
      "velocity": 0.3982801483922492,
      "x": -2.475483938679938,
      "y": 3.6431488121819444
    },
    {
      "accepted": true,
      "anchorsUsed": 6,
      "dt": 0.065,
      "rms": 2.171610106456242,
      "time": 1759401181816,
      "velocity": 0.4022754116360541,
      "x": -2.475483938679938,
      "y": 3.6431488121819444
    },
    {
      "accepted": true,
      "anchorsUsed": 6,
      "dt": 0.062,
      "rms": 2.171610106456242,
      "time": 1759401181878,
      "velocity": 0.40534124894867596,
      "x": -2.475483938679938,
      "y": 3.6431488121819444
    },
    {
      "accepted": true,
      "anchorsUsed": 6,
      "dt": 0.063,
      "rms": 2.171610106456242,
      "time": 1759401181941,
      "velocity": 0.40751017449444654,
      "x": -2.475483938679938,
      "y": 3.6431488121819444
    },
    {
      "accepted": true,
      "anchorsUsed": 6,
      "dt": 0.224,
      "rms": 2.171610106456242,
      "time": 1759401182165,
      "velocity": 0.40681711390785485,
      "x": -2.475483938679938,
      "y": 3.6431488121819444
    },
    {
      "accepted": true,
      "anchorsUsed": 6,
      "dt": 0.063,
      "rms": 2.171610106456242,
      "time": 1759401182228,
      "velocity": 0.4052805352963107,
      "x": -2.475483938679938,
      "y": 3.6431488121819444
    },
    {
      "accepted": true,
      "anchorsUsed": 6,
      "dt": 0.063,
      "rms": 2.171610106456242,
      "time": 1759401182291,
      "velocity": 0.40295261301868224,
      "x": -2.475483938679938,
      "y": 3.6431488121819444
    },
    {
      "accepted": true,
      "anchorsUsed": 6,
      "dt": 0.063,
      "rms": 2.171610106456242,
      "time": 1759401182354,
      "velocity": 0.3998847458664979,
      "x": -2.475483938679938,
      "y": 3.6431488121819444
    },
    {
      "accepted": true,
      "anchorsUsed": 6,
      "dt": 0.064,
      "rms": 2.171610106456242,
      "time": 1759401182418,
      "velocity": 0.39610963122866955,
      "x": -2.475483938679938,
      "y": 3.6431488121819444
    }
  ],
  "sessionId": "10001",
  "source": "BLT+Kalman",
  "startTimeMs": 1
}